{
  "_class": "shapePath",
  "booleanOperation": 0,
  "do_objectID": "9B3C172A-6BE1-44F5-8AE3-451ACA1AD982",
  "edited": false,
  "exportOptions": {
    "_class": "exportOptions",
    "exportFormats": [
    ],
    "includedLayerIds": [
    ],
    "layerOptions": 0,
    "shouldTrim": false
  },
  "frame": {
    "_class": "rect",
    "constrainProportions": false,
    "height": 191.1025989953466,
    "width": 273,
    "x": -0.9999990000000025,
    "y": -8.26079204677184
  },
  "isFlippedHorizontal": false,
  "isFlippedVertical": false,
  "isLocked": false,
  "isVisible": true,
  "layerListExpandedType": 0,
  "name": "Shape sp-3-0",
  "nameIsFixed": false,
  "path": {
    "_class": "path",
    "isClosed": true,
    "pointRadiusBehaviour": 0,
    "points": [
      {
        "_class": "curvePoint",
        "cornerRadius": 0,
        "curveFrom": "{0.003663, 0.043227000000000002}",
        "curveMode": 1,
        "curveTo": "{0.003663, 0.043227000000000002}",
        "hasCurveFrom": false,
        "hasCurveTo": false,
        "point": "{0.003663, 0.043227000000000002}"
      },
      {
        "_class": "curvePoint",
        "cornerRadius": 0,
        "curveFrom": "{0.99633700000000003, 0.043227000000000002}",
        "curveMode": 1,
        "curveTo": "{0.99633700000000003, 0.043227000000000002}",
        "hasCurveFrom": false,
        "hasCurveTo": false,
        "point": "{0.99633700000000003, 0.043227000000000002}"
      },
      {
        "_class": "curvePoint",
        "cornerRadius": 0,
        "curveFrom": "{0.99633700000000003, 0.99559500000000001}",
        "curveMode": 1,
        "curveTo": "{0.99633700000000003, 0.99559500000000001}",
        "hasCurveFrom": false,
        "hasCurveTo": false,
        "point": "{0.99633700000000003, 0.99559500000000001}"
      },
      {
        "_class": "curvePoint",
        "cornerRadius": 0,
        "curveFrom": "{0.003663, 0.99559500000000001}",
        "curveMode": 1,
        "curveTo": "{0.003663, 0.99559500000000001}",
        "hasCurveFrom": false,
        "hasCurveTo": false,
        "point": "{0.003663, 0.99559500000000001}"
      }
    ]
  },
  "resizingConstraint": 63,
  "resizingType": 0,
  "rotation": 0,
  "shouldBreakMaskChain": false
}